__init__.py
cloudformation.py
cloud_handler-0.0.1.dist-info/LICENSE
cloud_handler-0.0.1.dist-info/METADATA
cloud_handler-0.0.1.dist-info/WHEEL
cloud_handler-0.0.1.dist-info/top_level.txt
cloud_handler-0.0.1.dist-info/RECORD
